README.md
setup.py
byteball_rpc_client/__init__.py
byteball_rpc_client/client.py
byteball_rpc_client/exceptions.py
byteball_rpc_client.egg-info/PKG-INFO
byteball_rpc_client.egg-info/SOURCES.txt
byteball_rpc_client.egg-info/dependency_links.txt
byteball_rpc_client.egg-info/requires.txt
byteball_rpc_client.egg-info/top_level.txt