Metadata-Version: 1.0
Name: byteball-rpc-client
Version: 0.0.1
Summary: A Python JSON-RPC client for the headless wallet
Home-page: https://github.com/emre/byteball-rpc-client
Author: emre yilmaz
Author-email: mail@emreyilmaz.me
License: MIT
Platform: UNKNOWN
